{
  "pageTitle": "Blog",
  "metaDescription": "Bleiben Sie auf dem neuesten Stand der Trends in der Bauindustrie, Werkzeuginnovationen und Projekteinblicke mit dem ScrewFast Blog.",
  "ogTitle": "Blog der Bauindustrie | ScrewFast",
  "title": "Ihr Tor zur Bauexzellenz",
  "subTitle": "Entdecken Sie die neuesten Nachrichten, Tipps und Einblicke aus der Welt der Konstruktion und des Handwerks.",
  "secondTitle": "Einblicke",
  "secondSubTitle": "Bleiben Sie auf dem neuesten Stand der Trends in der Bauindustrie, Werkzeuginnovationen und Projekteinblicke."
}